pockethernet/__init__.py
pockethernet/__main__.py
pockethernet/crc16.py
pockethernet/ethernet.py
pockethernet/testresult.py
pockethernet-0.7.0.dist-info/METADATA
pockethernet-0.7.0.dist-info/WHEEL
pockethernet-0.7.0.dist-info/entry_points.txt
pockethernet-0.7.0.dist-info/top_level.txt
pockethernet-0.7.0.dist-info/RECORD
